fuzzylite/__init__.py
fuzzylite/activation.py
fuzzylite/benchmark.py
fuzzylite/defuzzifier.py
fuzzylite/engine.py
fuzzylite/examples/__init__.py
fuzzylite/examples/hybrid/__init__.py
fuzzylite/examples/hybrid/obstacle_avoidance.fld
fuzzylite/examples/hybrid/obstacle_avoidance.fll
fuzzylite/examples/hybrid/obstacle_avoidance.py
fuzzylite/examples/hybrid/tipper.fld
fuzzylite/examples/hybrid/tipper.fll
fuzzylite/examples/hybrid/tipper.py
fuzzylite/examples/mamdani/__init__.py
fuzzylite/examples/mamdani/all_terms.fld
fuzzylite/examples/mamdani/all_terms.fll
fuzzylite/examples/mamdani/all_terms.py
fuzzylite/examples/mamdani/laundry.fld
fuzzylite/examples/mamdani/laundry.fll
fuzzylite/examples/mamdani/laundry.py
fuzzylite/examples/mamdani/matlab/__init__.py
fuzzylite/examples/mamdani/matlab/mam21.fld
fuzzylite/examples/mamdani/matlab/mam21.fll
fuzzylite/examples/mamdani/matlab/mam21.py
fuzzylite/examples/mamdani/matlab/mam22.fld
fuzzylite/examples/mamdani/matlab/mam22.fll
fuzzylite/examples/mamdani/matlab/mam22.py
fuzzylite/examples/mamdani/matlab/shower.fld
fuzzylite/examples/mamdani/matlab/shower.fll
fuzzylite/examples/mamdani/matlab/shower.py
fuzzylite/examples/mamdani/matlab/tank.fld
fuzzylite/examples/mamdani/matlab/tank.fll
fuzzylite/examples/mamdani/matlab/tank.py
fuzzylite/examples/mamdani/matlab/tank2.fld
fuzzylite/examples/mamdani/matlab/tank2.fll
fuzzylite/examples/mamdani/matlab/tank2.py
fuzzylite/examples/mamdani/matlab/tipper.fld
fuzzylite/examples/mamdani/matlab/tipper.fll
fuzzylite/examples/mamdani/matlab/tipper.py
fuzzylite/examples/mamdani/matlab/tipper1.fld
fuzzylite/examples/mamdani/matlab/tipper1.fll
fuzzylite/examples/mamdani/matlab/tipper1.py
fuzzylite/examples/mamdani/obstacle_avoidance.fld
fuzzylite/examples/mamdani/obstacle_avoidance.fll
fuzzylite/examples/mamdani/obstacle_avoidance.py
fuzzylite/examples/mamdani/octave/__init__.py
fuzzylite/examples/mamdani/octave/investment_portfolio.fld
pyfuzzylite-8.0.6.dist-info/LICENSE.FuzzyLite.txt
pyfuzzylite-8.0.6.dist-info/LICENSE.GPL.txt
pyfuzzylite-8.0.6.dist-info/METADATA
pyfuzzylite-8.0.6.dist-info/WHEEL
pyfuzzylite-8.0.6.dist-info/RECORD
