Metadata-Version: 2.3
Name: pyfuzzylite
Version: 8.0.6
Summary: a fuzzy logic control library in Python
License: Proprietary
Keywords: fuzzy logic control,soft computing,artificial intelligence
Author: Juan Rada-Vilela, PhD
Author-email: jcrada@fuzzylite.com
Maintainer: Juan Rada-Vilela, PhD
Maintainer-email: jcrada@fuzzylite.com
Requires-Python: >=3.9,<4.0
Classifier: Development Status :: 5 - Production/Stable
Classifier: Intended Audience :: Developers
Classifier: Intended Audience :: Science/Research
Classifier: License :: OSI Approved :: GNU General Public License v3 (GPLv3)
Classifier: License :: Other/Proprietary License
Classifier: Operating System :: OS Independent
Classifier: Programming Language :: Python :: 3
Classifier: Programming Language :: Python :: 3.9
Classifier: Programming Language :: Python :: 3.10
Classifier: Programming Language :: Python :: 3.11
Classifier: Programming Language :: Python :: 3.12
Classifier: Programming Language :: Python :: 3.13
Classifier: Programming Language :: Python :: 3 :: Only
Classifier: Topic :: Scientific/Engineering :: Artificial Intelligence
Classifier: Topic :: Scientific/Engineering :: Mathematics
Classifier: Topic :: Software Development :: Libraries
Classifier: Typing :: Typed
Requires-Dist: numpy (>=1.20,<2.0)
Project-URL: Bug Tracker, https://github.com/fuzzylite/pyfuzzylite/issues
Project-URL: Documentation, https://fuzzylite.github.io/pyfuzzylite/
Project-URL: Repository, https://github.com/fuzzylite/pyfuzzylite.git
Project-URL: Source Code, https://github.com/fuzzylite/pyfuzzylite
